README.md
setup.cfg
setup.py
synym.py
synym.egg-info/PKG-INFO
synym.egg-info/SOURCES.txt
synym.egg-info/dependency_links.txt
synym.egg-info/entry_points.txt
synym.egg-info/requires.txt
synym.egg-info/top_level.txt