Metadata-Version: 1.1
Name: synym
Version: 0.1
Summary: CLI tool to list synonyms for a word from thesaurus.com
Home-page: https://github.com/rahilwazir/synym
Author: Rahil Wazir
Author-email: rahilwazirali@gmail.com
License: UNKNOWN
Download-URL: https://github.com/rahilwazir/synym/archive/0.1.tar.gz
Platform: UNKNOWN
